dophon_db/__init__.py
dophon_db/const/__init__.py
dophon_db/const/regix_str.py
dophon_db/mongo/__init__.py
dophon_db/mongo/Pool.py
dophon_db/mysql/__init__.py
dophon_db/mysql/Connection.py
dophon_db/mysql/orm/__init__.py
dophon_db/mysql/orm/db_obj/__init__.py
dophon_db/mysql/orm/db_obj/function_class/__init__.py
dophon_db/mysql/orm/db_obj/type_dict.py
dophon_db/mysql/orm/manager_init.py
dophon_db/mysql/orm/query_structor.py
dophon_db/mysql/Pool.py
dophon_db/mysql/sql_util/__init__.py
dophon_db/mysql/xml/__init__.py
dophon_db/mysql/xml/binlog/__init__.py
dophon_db/mysql/xml/binlog/Schued.py
dophon_db/mysql/xml/binlog/ZipBinLog.py
dophon_db/mysql/xml/cluster.py
dophon_db/mysql/xml/core.py
dophon_db/mysql/xml/PageHelper.py
dophon_db/mysql/xml/remote/__init__.py
dophon_db/mysql/xml/remote/Cell.py
dophon_db/mysql/xml/single.py
dophon_db/reader/__init__.py
dophon_db/sqllite/__init__.py
dophon_db/sqllite/db_init.py
dophon_db/utils/__init__.py
dophon_db/utils/dynamic_import.py
dophon_db-1.3.1.post1.dist-info/LICENSE
dophon_db-1.3.1.post1.dist-info/WHEEL
dophon_db-1.3.1.post1.dist-info/METADATA
dophon_db-1.3.1.post1.dist-info/RECORD
