Metadata-Version: 2.1
Name: dophon-db
Version: 1.3.1.post1
Summary: dophon database module
License: Apache 2.0
Author: CallMeE
Author-email: ealohu@163.com
Requires-Python: >=3.6,<4.0
Classifier: License :: Other/Proprietary License
Classifier: Programming Language :: Python :: 3
Classifier: Programming Language :: Python :: 3.6
Classifier: Programming Language :: Python :: 3.7
Classifier: Programming Language :: Python :: 3.8
Classifier: Programming Language :: Python :: 3.9
Requires-Dist: cryptography
Requires-Dist: dbutils
Requires-Dist: dophon-logger
Requires-Dist: dophon-properties
Requires-Dist: pymysql (>=1.0.2,<1.1.0)
Requires-Dist: schedule
Requires-Dist: urllib3
